.gitignore
MANIFEST.in
README.rst
bootstrap.py
buildout.cfg
setup.py
collective/__init__.py
collective.js.moment.egg-info/PKG-INFO
collective.js.moment.egg-info/SOURCES.txt
collective.js.moment.egg-info/dependency_links.txt
collective.js.moment.egg-info/entry_points.txt
collective.js.moment.egg-info/namespace_packages.txt
collective.js.moment.egg-info/not-zip-safe
collective.js.moment.egg-info/requires.txt
collective.js.moment.egg-info/top_level.txt
collective/js/__init__.py
collective/js/moment/__init__.py
collective/js/moment/configure.zcml
collective/js/moment/example/__init__.py
collective/js/moment/example/configure.zcml
collective/js/moment/example/example.pt
collective/js/moment/example/css/app.css
collective/js/moment/profiles/default/jsregistry.xml
collective/js/moment/profiles/default/metadata.xml
collective/js/moment/resources/moment.js
collective/js/moment/resources/lang/bg.js
collective/js/moment/resources/lang/ca.js
collective/js/moment/resources/lang/cv.js
collective/js/moment/resources/lang/da.js
collective/js/moment/resources/lang/de.js
collective/js/moment/resources/lang/en-ca.js
collective/js/moment/resources/lang/en-gb.js
collective/js/moment/resources/lang/es.js
collective/js/moment/resources/lang/eu.js
collective/js/moment/resources/lang/fi.js
collective/js/moment/resources/lang/fr-ca.js
collective/js/moment/resources/lang/fr.js
collective/js/moment/resources/lang/gl.js
collective/js/moment/resources/lang/hu.js
collective/js/moment/resources/lang/is.js
collective/js/moment/resources/lang/it.js
collective/js/moment/resources/lang/ja.js
collective/js/moment/resources/lang/jp.js
collective/js/moment/resources/lang/ko.js
collective/js/moment/resources/lang/kr.js
collective/js/moment/resources/lang/nb.js
collective/js/moment/resources/lang/nl.js
collective/js/moment/resources/lang/pl.js
collective/js/moment/resources/lang/pt-br.js
collective/js/moment/resources/lang/pt.js
collective/js/moment/resources/lang/ro.js
collective/js/moment/resources/lang/ru.js
collective/js/moment/resources/lang/sv.js
collective/js/moment/resources/lang/tr.js
collective/js/moment/resources/lang/zh-cn.js
collective/js/moment/resources/lang/zh-tw.js
collective/js/moment/upgrades/__init__.py
collective/js/moment/upgrades/configure.zcml
collective/js/moment/upgrades/v1000_to_1001.py
docs/HISTORY.txt