Metadata-Version: 1.1
Name: collective.js.moment
Version: 1.0.1
Summary: moment.js for Plone
Home-page: https://github.com/kingel/collective.js.moment
Author: UNKNOWN
Author-email: UNKNOWN
License: GPL
Platform: UNKNOWN
Classifier: Programming Language :: Python
